{
    "226": {
        "id": "226",
        "img": "https://img3.doubanio.com/view/photo/s_ratio_poster/public/p792423963.jpg",
        "title": "千钧一发",
        "tags": {
            "时间": "1997",
            "国家": [
                "美国"
            ],
            "属性": [
                "剧情",
                "科幻",
                "惊悚"
            ]
        },
        "score": 8.8,
        "quote": "一部能引人思考的科幻励志片。",
        "href": "https://movie.douban.com/subject/1300117/"
    },
    "227": {
        "id": "227",
        "img": "https://img9.doubanio.com/view/photo/s_ratio_poster/public/p721429854.jpg",
        "title": "哈利·波特与死亡圣器(上)",
        "tags": {
            "时间": "2010",
            "国家": [
                "英国",
                "美国"
            ],
            "属性": [
                "奇幻",
                "冒险"
            ]
        },
        "score": 8.6,
        "quote": "最忠于原著的一部。",
        "href": "https://movie.douban.com/subject/2051007/"
    },
    "228": {
        "id": "228",
        "img": "https://img9.doubanio.com/view/photo/s_ratio_poster/public/p2187896734.jpg",
        "title": "彗星来的那一夜",
        "tags": {
            "时间": "2013",
            "国家": [
                "美国",
                "英国"
            ],
            "属性": [
                "科幻",
                "悬疑",
                "惊悚"
            ]
        },
        "score": 8.6,
        "quote": "小成本大魅力。",
        "href": "https://movie.douban.com/subject/25807345/"
    },
    "229": {
        "id": "229",
        "img": "https://img2.doubanio.com/view/photo/s_ratio_poster/public/p2160195181.jpg",
        "title": "白日梦想家",
        "tags": {
            "时间": "2013",
            "国家": [
                "美国",
                "英国"
            ],
            "属性": [
                "剧情",
                "喜剧",
                "冒险"
            ]
        },
        "score": 8.6,
        "quote": "",
        "href": "https://movie.douban.com/subject/2133323/"
    },
    "230": {
        "id": "230",
        "img": "https://img1.doubanio.com/view/photo/s_ratio_poster/public/p2237136718.jpg",
        "title": "萤火虫之墓",
        "tags": {
            "时间": "1988",
            "国家": [
                "日本"
            ],
            "属性": [
                "动画",
                "剧情",
                "战争"
            ]
        },
        "score": 8.7,
        "quote": "幸福是生生不息，却难以触及的远。 ",
        "href": "https://movie.douban.com/subject/1293318/"
    },
    "231": {
        "id": "231",
        "img": "https://img1.doubanio.com/view/photo/s_ratio_poster/public/p443461390.jpg",
        "title": "黑客帝国2：重装上阵",
        "tags": {
            "时间": "2003",
            "国家": [
                "美国"
            ],
            "属性": [
                "动作",
                "科幻"
            ]
        },
        "score": 8.7,
        "quote": "一个精彩的世界观正在缓缓建立。",
        "href": "https://movie.douban.com/subject/1304141/"
    },
    "232": {
        "id": "232",
        "img": "https://img1.doubanio.com/view/photo/s_ratio_poster/public/p2507709428.jpg",
        "title": "奇迹男孩",
        "tags": {
            "时间": "2017",
            "国家": [
                "美国",
                "中国香港"
            ],
            "属性": [
                "剧情",
                "儿童",
                "家庭"
            ]
        },
        "score": 8.6,
        "quote": "世界不完美，爱会有奇迹。",
        "href": "https://movie.douban.com/subject/26787574/"
    },
    "233": {
        "id": "233",
        "img": "https://img3.doubanio.com/view/photo/s_ratio_poster/public/p2264592493.jpg",
        "title": "火星救援",
        "tags": {
            "时间": "2015",
            "国家": [
                "英国",
                "美国",
                "匈牙利",
                "约旦"
            ],
            "属性": [
                "剧情",
                "科幻",
                "冒险"
            ]
        },
        "score": 8.5,
        "quote": "",
        "href": "https://movie.douban.com/subject/25864085/"
    },
    "234": {
        "id": "234",
        "img": "https://img3.doubanio.com/view/photo/s_ratio_poster/public/p2457609817.jpg",
        "title": "二十二",
        "tags": {
            "时间": "2015",
            "国家": [
                "中国大陆"
            ],
            "属性": [
                "纪录片"
            ]
        },
        "score": 8.7,
        "quote": "有一些东西不应该被遗忘。",
        "href": "https://movie.douban.com/subject/26430107/"
    },
    "235": {
        "id": "235",
        "img": "https://img2.doubanio.com/view/photo/s_ratio_poster/public/p792282381.jpg",
        "title": "战争之王",
        "tags": {
            "时间": "2005",
            "国家": [
                "美国",
                "德国"
            ],
            "属性": [
                "剧情",
                "犯罪"
            ]
        },
        "score": 8.7,
        "quote": "做一颗让别人需要你的棋子。",
        "href": "https://movie.douban.com/subject/1419936/"
    },
    "236": {
        "id": "236",
        "img": "https://img3.doubanio.com/view/photo/s_ratio_poster/public/p1244017073.jpg",
        "title": "血钻",
        "tags": {
            "时间": "2006",
            "国家": [
                "美国",
                "德国",
                "英国"
            ],
            "属性": [
                "剧情",
                "惊悚",
                "冒险"
            ]
        },
        "score": 8.7,
        "quote": "每个美丽事物背后都是滴血的现实。",
        "href": "https://movie.douban.com/subject/1428175/"
    },
    "237": {
        "id": "237",
        "img": "https://img1.doubanio.com/view/photo/s_ratio_poster/public/p443403700.jpg",
        "title": "哈利·波特与凤凰社",
        "tags": {
            "时间": "2007",
            "国家": [
                "英国",
                "美国"
            ],
            "属性": [
                "奇幻",
                "冒险"
            ]
        },
        "score": 8.5,
        "quote": "",
        "href": "https://movie.douban.com/subject/1457217/"
    },
    "238": {
        "id": "238",
        "img": "https://img3.doubanio.com/view/photo/s_ratio_poster/public/p1254404823.jpg",
        "title": "大红灯笼高高挂",
        "tags": {
            "时间": "1991",
            "国家": [
                "中国大陆",
                "中国香港",
                "中国台湾"
            ],
            "属性": [
                "剧情"
            ]
        },
        "score": 8.8,
        "quote": "",
        "href": "https://movie.douban.com/subject/1293323/"
    },
    "239": {
        "id": "239",
        "img": "https://img1.doubanio.com/view/photo/s_ratio_poster/public/p2375245718.jpg",
        "title": "步履不停",
        "tags": {
            "时间": "2008",
            "国家": [
                "日本"
            ],
            "属性": [
                "剧情",
                "家庭"
            ]
        },
        "score": 8.8,
        "quote": "日本的家庭电影已经是世界巅峰了，步履不停是巅峰中的佳作。",
        "href": "https://movie.douban.com/subject/2222996/"
    },
    "240": {
        "id": "240",
        "img": "https://img9.doubanio.com/view/photo/s_ratio_poster/public/p2215102596.jpg",
        "title": "千年女优",
        "tags": {
            "时间": "2001",
            "国家": [
                "日本"
            ],
            "属性": [
                "动画",
                "剧情",
                "爱情"
            ]
        },
        "score": 8.8,
        "quote": "爱情是一场没有尽头的虚幻追逐。",
        "href": "https://movie.douban.com/subject/1307394/"
    },
    "241": {
        "id": "241",
        "img": "https://img9.doubanio.com/view/photo/s_ratio_poster/public/p2259715855.jpg",
        "title": "房间",
        "tags": {
            "时间": "2015",
            "国家": [
                "爱尔兰",
                "加拿大",
                "英国",
                "美国"
            ],
            "属性": [
                "剧情",
                "家庭"
            ]
        },
        "score": 8.8,
        "quote": "被偷走的岁月，被伤害的生命，被禁锢的灵魂，终将被希望和善意救赎。",
        "href": "https://movie.douban.com/subject/25724855/"
    },
    "242": {
        "id": "242",
        "img": "https://img9.doubanio.com/view/photo/s_ratio_poster/public/p667644866.jpg",
        "title": "谍影重重2",
        "tags": {
            "时间": "2004",
            "国家": [
                "美国",
                "德国"
            ],
            "属性": [
                "动作",
                "悬疑",
                "惊悚"
            ]
        },
        "score": 8.7,
        "quote": "谁说王家卫镜头很晃？",
        "href": "https://movie.douban.com/subject/1308767/"
    },
    "243": {
        "id": "243",
        "img": "https://img1.doubanio.com/view/photo/s_ratio_poster/public/p2351134499.jpg",
        "title": "魂断蓝桥",
        "tags": {
            "时间": "1940",
            "国家": [
                "美国"
            ],
            "属性": [
                "剧情",
                "爱情",
                "战争"
            ]
        },
        "score": 8.8,
        "quote": "中国式内在的美国电影。",
        "href": "https://movie.douban.com/subject/1293964/"
    },
    "244": {
        "id": "244",
        "img": "https://img1.doubanio.com/view/photo/s_ratio_poster/public/p2535851348.jpg",
        "title": "蜘蛛侠：平行宇宙",
        "tags": {
            "时间": "2018",
            "国家": [
                "美国"
            ],
            "属性": [
                "动作",
                "科幻",
                "动画",
                "冒险"
            ]
        },
        "score": 8.6,
        "quote": "",
        "href": "https://movie.douban.com/subject/26374197/"
    },
    "245": {
        "id": "245",
        "img": "https://img3.doubanio.com/view/photo/s_ratio_poster/public/p2577248102.jpg",
        "title": "弱点",
        "tags": {
            "时间": "2009",
            "国家": [
                "美国"
            ],
            "属性": [
                "剧情",
                "家庭",
                "传记",
                "运动"
            ]
        },
        "score": 8.7,
        "quote": "拍掉身上的悲伤，从今天开始重新踏上追梦之旅。",
        "href": "https://movie.douban.com/subject/3552028/"
    },
    "246": {
        "id": "246",
        "img": "https://img2.doubanio.com/view/photo/s_ratio_poster/public/p1597183981.jpg",
        "title": "谍影重重",
        "tags": {
            "时间": "2002",
            "国家": [
                "美国",
                "德国",
                "捷克"
            ],
            "属性": [
                "动作",
                "悬疑",
                "惊悚"
            ]
        },
        "score": 8.6,
        "quote": "哗啦啦啦啦，天在下雨，哗啦啦啦啦，云在哭泣……找自己。",
        "href": "https://movie.douban.com/subject/1304102/"
    },
    "247": {
        "id": "247",
        "img": "https://img3.doubanio.com/view/photo/s_ratio_poster/public/p2525770523.jpg",
        "title": "阿飞正传",
        "tags": {
            "时间": "1990",
            "国家": [
                "中国香港"
            ],
            "属性": [
                "犯罪",
                "剧情",
                "爱情"
            ]
        },
        "score": 8.5,
        "quote": "王家卫是一种风格，张国荣是一个代表。",
        "href": "https://movie.douban.com/subject/1305690/"
    },
    "248": {
        "id": "248",
        "img": "https://img1.doubanio.com/view/photo/s_ratio_poster/public/p1140984198.jpg",
        "title": "朗读者",
        "tags": {
            "时间": "2008",
            "国家": [
                "美国",
                "德国"
            ],
            "属性": [
                "剧情",
                "爱情"
            ]
        },
        "score": 8.6,
        "quote": "当爱情跨越年龄的界限，它似乎能变得更久远一点，成为一种责任，一种水到渠成的相濡以沫。 ",
        "href": "https://movie.douban.com/subject/2213597/"
    },
    "249": {
        "id": "249",
        "img": "https://img1.doubanio.com/view/photo/s_ratio_poster/public/p2374067318.jpg",
        "title": "隐藏人物",
        "tags": {
            "时间": "2016",
            "国家": [
                "美国"
            ],
            "属性": [
                "剧情",
                "传记",
                "历史"
            ]
        },
        "score": 8.9,
        "quote": "",
        "href": "https://movie.douban.com/subject/26615208/"
    },
    "250": {
        "id": "250",
        "img": "https://img3.doubanio.com/view/photo/s_ratio_poster/public/p2250287733.jpg",
        "title": "再次出发之纽约遇见你",
        "tags": {
            "时间": "2013",
            "国家": [
                "美国"
            ],
            "属性": [
                "喜剧",
                "爱情",
                "音乐"
            ]
        },
        "score": 8.6,
        "quote": "爱我就给我看你的播放列表。",
        "href": "https://movie.douban.com/subject/6874403/"
    }
}